xgwbinary/__init__.py
xgwbinary-0.1.dist-info/LICENSE.txt
xgwbinary-0.1.dist-info/METADATA
xgwbinary-0.1.dist-info/WHEEL
xgwbinary-0.1.dist-info/top_level.txt
xgwbinary-0.1.dist-info/RECORD
