Metadata-Version: 2.1
Name: xgwbinary
Version: 0.1
Summary: A simple interpreter for my version of binary.
Author: xoxogamewolf
Author-email: xoxogamewolf@gmail.com
Classifier: Programming Language :: Python :: 3
Classifier: License :: OSI Approved :: MIT License
Classifier: Operating System :: OS Independent
License-File: LICENSE.txt
